{
    "criteria": {
      "has_music_disc_creator": {
        "conditions": {
          "items": [
            {
              "items": [
                "minecraft:music_disc_creator",
                "minecraft:music_disc_creator_music_box"
              ]
            }
          ]
        },
        "trigger": "minecraft:inventory_changed"
      },
      "has_the_recipe": {
        "conditions": {
          "recipe": "music_disc_creator"
        },
        "trigger": "minecraft:recipe_unlocked"
      }
    },
    "requirements": [
      [
        "has_music_disc_creator",
        "has_the_recipe"
      ]
    ],
    "rewards": {
      "recipes": [
        "music_disc_creator"
      ]
    }
  }